zyjared_fs/__init__.py
zyjared_fs/fs.py
zyjared_fs-0.1.1.dist-info/METADATA
zyjared_fs-0.1.1.dist-info/WHEEL
zyjared_fs-0.1.1.dist-info/top_level.txt
zyjared_fs-0.1.1.dist-info/RECORD
