Metadata-Version: 2.1
Name: zyjared-fs
Version: 0.1.1
Summary: simple tools for file or path
Home-page: https://github.com/zyjared/kit-python
Author: Jared Zhang
Author-email: zyjared@outlook.com
Classifier: Programming Language :: Python :: 3.6
Classifier: License :: OSI Approved :: MIT License
Classifier: Operating System :: OS Independent
Requires-Python: >=3.6
